fastapi_dddocr/__init__.py
fastapi_dddocr/fastapi_dddocr.py
fastapi_dddocr-0.0.2.dist-info/LICENSE.txt
fastapi_dddocr-0.0.2.dist-info/METADATA
fastapi_dddocr-0.0.2.dist-info/WHEEL
fastapi_dddocr-0.0.2.dist-info/top_level.txt
fastapi_dddocr-0.0.2.dist-info/RECORD
