Metadata-Version: 2.1
Name: fastapi-dddocr
Version: 0.0.2
Summary: 这一个api接口，主要是用于验证码识别
Home-page: 
Author: jixn
Author-email: 1770550067@qq.com
Classifier: Programming Language :: Python :: 3
Classifier: License :: OSI Approved :: MIT License
Classifier: Operating System :: OS Independent
Requires-Python: >=3.8
License-File: LICENSE.txt
Requires-Dist: ddddocr
Requires-Dist: fastapi
Requires-Dist: uvicorn
